coronavirus/__init__.py
coronavirus-1.1.1.dist-info/LICENSE
coronavirus-1.1.1.dist-info/LICENSE.md
coronavirus-1.1.1.dist-info/METADATA
coronavirus-1.1.1.dist-info/WHEEL
coronavirus-1.1.1.dist-info/top_level.txt
coronavirus-1.1.1.dist-info/RECORD
