Metadata-Version: 2.1
Name: coronavirus
Version: 1.1.1
Summary: Asynchronous Python client for getting Corona virus info.
Home-page: https://github.com/nabucasa/coronavirus
Author: Nabu Casa
Author-email: opensource@nabucasa.com
License: MIT license
Keywords: corona,coronavirus,ncov19,api,async,client
Platform: UNKNOWN
Classifier: Framework :: AsyncIO
Classifier: Intended Audience :: Developers
Classifier: License :: OSI Approved :: MIT License
Classifier: Natural Language :: English
Classifier: Programming Language :: Python :: 3.7
Classifier: Programming Language :: Python :: 3.8
Classifier: Programming Language :: Python :: 3
Classifier: Topic :: Software Development :: Libraries :: Python Modules
Requires-Dist: aiohttp (>=3.0.0)
